pyucs/__init__.py
pyucs/credentials/__init__.py
pyucs/credentials/credstore.py
pyucs/influx/__init__.py
pyucs/influx/client.py
pyucs/log/__init__.py
pyucs/log/decorators.py
pyucs/log/setup.py
pyucs/logging/__init__.py
pyucs/logging/handler.py
pyucs/statsd/__init__.py
pyucs/statsd/collector.py
pyucs/statsd/parse.py
pyucs/statsd/portstats.py
pyucs/ucs/__init__.py
pyucs/ucs/handler.py
pyucs/ucs/vlan/__init__.py
pyucs/ucs/vlan/comparison.py
pyucs/ucs/vnic/__init__.py
pyucs/ucs/vnic/vnic.py
pyucs_samn-2.0.6.dist-info/LICENSE
pyucs_samn-2.0.6.dist-info/METADATA
pyucs_samn-2.0.6.dist-info/WHEEL
pyucs_samn-2.0.6.dist-info/top_level.txt
pyucs_samn-2.0.6.dist-info/RECORD
