Metadata-Version: 2.1
Name: pyucs-samn
Version: 2.0.6
Summary: Customized UCS Python Module
Home-page: https://github.com/ToxicSamN/pyucs
Author: Sammy Shuck github.com/ToxicSamN
Author-email: UNKNOWN
License: Apache
Keywords: pyucs,pyucs-samn
Platform: UNKNOWN
Requires-Dist: influxdb (>=5.2.1)
Requires-Dist: pycrypt-samn (>=1.3.2)
Requires-Dist: pyparsing (>=2.3.1)
Requires-Dist: python-dateutil (>=2.8.0)
Requires-Dist: pytz (>=2018.9)
Requires-Dist: ucsmsdk (>=0.9.8)
